console_logger/__init__.py
console_logger-0.0.9.dist-info/LICENSE.txt
console_logger-0.0.9.dist-info/METADATA
console_logger-0.0.9.dist-info/WHEEL
console_logger-0.0.9.dist-info/top_level.txt
console_logger-0.0.9.dist-info/RECORD
