Metadata-Version: 2.1
Name: console-logger
Version: 0.0.9
Summary: Yet another logging package for Python
Home-page: UNKNOWN
Author: Mikhail Buchnev
Author-email: me@buchnev.page
License: MIT License
Project-URL: Source, https://github.com/m1buchnev/console_logger
Keywords: log,logging,logger,console
Platform: UNKNOWN
Classifier: Development Status :: 3 - Alpha
Classifier: License :: OSI Approved :: MIT License
Classifier: Operating System :: OS Independent
Classifier: Programming Language :: Python :: 3 :: Only
Requires-Python: >=3.7
License-File: LICENSE.txt
